{"owner_id":"1524967","members":{"1542191":{"global_score":0,"name":"Stephanie Brown","stars":44,"last_star_ts":1640428915,"completion_day_level":{"6":{"1":{"get_star_ts":1638791889},"2":{"get_star_ts":1638793399}},"16":{"1":{"get_star_ts":1639653874},"2":{"get_star_ts":1639654926}},"20":{"1":{"get_star_ts":1640001076},"2":{"get_star_ts":1640004580}},"5":{"1":{"get_star_ts":1638703616},"2":{"get_star_ts":1638705113}},"9":{"1":{"get_star_ts":1639051597},"2":{"get_star_ts":1639053206}},"8":{"2":{"get_star_ts":1638965225},"1":{"get_star_ts":1638956733}},"22":{"1":{"get_star_ts":1640176914}},"11":{"2":{"get_star_ts":1639226582},"1":{"get_star_ts":1639226341}},"17":{"1":{"get_star_ts":1639750484},"2":{"get_star_ts":1639768555}},"14":{"1":{"get_star_ts":1639483826},"2":{"get_star_ts":1639523126}},"23":{"1":{"get_star_ts":1640262847},"2":{"get_star_ts":1640302384}},"3":{"2":{"get_star_ts":1638536885},"1":{"get_star_ts":1638534870}},"18":{"1":{"get_star_ts":1639864361},"2":{"get_star_ts":1639866657}},"12":{"1":{"get_star_ts":1639319260},"2":{"get_star_ts":1639321514}},"10":{"1":{"get_star_ts":1639141698},"2":{"get_star_ts":1639142846}},"21":{"2":{"get_star_ts":1640126279},"1":{"get_star_ts":1640088857}},"13":{"2":{"get_star_ts":1639398754},"1":{"get_star_ts":1639398161}},"7":{"2":{"get_star_ts":1638878487},"1":{"get_star_ts":1638877983}},"1":{"2":{"get_star_ts":1638364534},"1":{"get_star_ts":1638363767}},"2":{"2":{"get_star_ts":1638446034},"1":{"get_star_ts":1638445635}},"15":{"1":{"get_star_ts":1639581660},"2":{"get_star_ts":1639591040}},"25":{"1":{"get_star_ts":1640428915}},"4":{"1":{"get_star_ts":1638657753},"2":{"get_star_ts":1638661124}}},"id":"1542191","local_score":411},"1636965":{"stars":26,"global_score":0,"name":"David G","local_score":158,"completion_day_level":{"3":{"2":{"get_star_ts":1638929751},"1":{"get_star_ts":1638917037}},"14":{"2":{"get_star_ts":1639535461},"1":{"get_star_ts":1639532449}},"15":{"1":{"get_star_ts":1639716584}},"4":{"1":{"get_star_ts":1639204225},"2":{"get_star_ts":1639240831}},"11":{"2":{"get_star_ts":1639446759},"1":{"get_star_ts":1639446483}},"8":{"2":{"get_star_ts":1639015784},"1":{"get_star_ts":1638940504}},"2":{"2":{"get_star_ts":1638898850},"1":{"get_star_ts":1638898391}},"9":{"1":{"get_star_ts":1639195910}},"1":{"2":{"get_star_ts":1638377941},"1":{"get_star_ts":1638377626}},"13":{"2":{"get_star_ts":1639410706},"1":{"get_star_ts":1639405287}},"5":{"2":{"get_star_ts":1638941903},"1":{"get_star_ts":1638933695}},"7":{"1":{"get_star_ts":1638886988},"2":{"get_star_ts":1638887748}},"6":{"2":{"get_star_ts":1638824411},"1":{"get_star_ts":1638824325}},"10":{"1":{"get_star_ts":1639182817},"2":{"get_star_ts":1639183851}}},"id":"1636965","last_star_ts":1639716584},"1524967":{"completion_day_level":{"4":{"2":{"get_star_ts":1638596282},"1":{"get_star_ts":1638595960}},"15":{"2":{"get_star_ts":1639624176},"1":{"get_star_ts":1639622733}},"1":{"2":{"get_star_ts":1638362224},"1":{"get_star_ts":1638361913}},"2":{"1":{"get_star_ts":1638444416},"2":{"get_star_ts":1638444541}},"21":{"2":{"get_star_ts":1640124109},"1":{"get_star_ts":1640086069}},"10":{"1":{"get_star_ts":1639159741},"2":{"get_star_ts":1639160487}},"12":{"1":{"get_star_ts":1639333130},"2":{"get_star_ts":1639333965}},"7":{"1":{"get_star_ts":1638877483},"2":{"get_star_ts":1638877842}},"19":{"1":{"get_star_ts":1640229947},"2":{"get_star_ts":1640230337}},"13":{"1":{"get_star_ts":1639395391},"2":{"get_star_ts":1639395864}},"14":{"2":{"get_star_ts":1639523520},"1":{"get_star_ts":1639523453}},"18":{"2":{"get_star_ts":1639835822},"1":{"get_star_ts":1639835393}},"3":{"1":{"get_star_ts":1638535763},"2":{"get_star_ts":1638537216}},"11":{"1":{"get_star_ts":1639229419},"2":{"get_star_ts":1639229739}},"17":{"1":{"get_star_ts":1639779476},"2":{"get_star_ts":1639779619}},"9":{"1":{"get_star_ts":1639048648},"2":{"get_star_ts":1639096747}},"8":{"2":{"get_star_ts":1638966610},"1":{"get_star_ts":1638965051}},"16":{"2":{"get_star_ts":1639801096},"1":{"get_star_ts":1639800278}},"6":{"2":{"get_star_ts":1638789688},"1":{"get_star_ts":1638788618}},"5":{"2":{"get_star_ts":1638742754},"1":{"get_star_ts":1638742195}},"20":{"2":{"get_star_ts":1640055218},"1":{"get_star_ts":1640039384}}},"id":"1524967","local_score":377,"last_star_ts":1640230337,"stars":42,"name":"Jessica Moore","global_score":0},"1533417":{"name":"Julia Buffinton","global_score":0,"stars":38,"last_star_ts":1640180804,"local_score":307,"completion_day_level":{"8":{"1":{"get_star_ts":1638963644},"2":{"get_star_ts":1638970311}},"22":{"1":{"get_star_ts":1640180804}},"9":{"1":{"get_star_ts":1639051372},"2":{"get_star_ts":1639095136}},"5":{"1":{"get_star_ts":1638710663},"2":{"get_star_ts":1638711196}},"20":{"2":{"get_star_ts":1640040436},"1":{"get_star_ts":1640040343}},"16":{"1":{"get_star_ts":1639705383}},"6":{"2":{"get_star_ts":1638807229},"1":{"get_star_ts":1638806293}},"18":{"1":{"get_star_ts":1639917541}},"3":{"2":{"get_star_ts":1638569486},"1":{"get_star_ts":1638568055}},"14":{"2":{"get_star_ts":1639523165},"1":{"get_star_ts":1639511831}},"17":{"1":{"get_star_ts":1639744247},"2":{"get_star_ts":1639744789}},"11":{"1":{"get_star_ts":1639255906},"2":{"get_star_ts":1639256314}},"2":{"1":{"get_star_ts":1638483189},"2":{"get_star_ts":1638489921}},"1":{"2":{"get_star_ts":1638408962},"1":{"get_star_ts":1638408426}},"7":{"1":{"get_star_ts":1638879156},"2":{"get_star_ts":1638879764}},"13":{"2":{"get_star_ts":1639448302},"1":{"get_star_ts":1639447743}},"21":{"1":{"get_star_ts":1640128370}},"10":{"2":{"get_star_ts":1639140000},"1":{"get_star_ts":1639138935}},"12":{"1":{"get_star_ts":1639328581},"2":{"get_star_ts":1639331106}},"4":{"1":{"get_star_ts":1638628206},"2":{"get_star_ts":1638628415}},"15":{"1":{"get_star_ts":1639847711},"2":{"get_star_ts":1639850179}}},"id":"1533417"},"1908664":{"completion_day_level":{"1":{"2":{"get_star_ts":1639347296},"1":{"get_star_ts":1639345986}},"4":{"1":{"get_star_ts":1639362511}},"3":{"1":{"get_star_ts":1639349685},"2":{"get_star_ts":1639354310}},"2":{"1":{"get_star_ts":1639347742},"2":{"get_star_ts":1639348234}}},"id":"1908664","local_score":15,"last_star_ts":1639362511,"stars":7,"name":"Jessica Conroy","global_score":0},"1975209":{"id":"1975209","completion_day_level":{},"local_score":0,"last_star_ts":"0","stars":0,"global_score":0,"name":"Simon Whittle"},"1562613":{"stars":19,"name":"Cindy Goss","global_score":0,"local_score":137,"completion_day_level":{"3":{"1":{"get_star_ts":1638554555},"2":{"get_star_ts":1638557827}},"4":{"2":{"get_star_ts":1638654067},"1":{"get_star_ts":1638643685}},"14":{"1":{"get_star_ts":1639524515}},"8":{"1":{"get_star_ts":1638964024}},"2":{"1":{"get_star_ts":1638459736},"2":{"get_star_ts":1638462218}},"9":{"1":{"get_star_ts":1639087234}},"1":{"2":{"get_star_ts":1638375537},"1":{"get_star_ts":1638373099}},"5":{"1":{"get_star_ts":1638736405},"2":{"get_star_ts":1638739369}},"7":{"2":{"get_star_ts":1638889949},"1":{"get_star_ts":1638885098}},"13":{"1":{"get_star_ts":1639439782},"2":{"get_star_ts":1639441166}},"6":{"1":{"get_star_ts":1638834855}},"10":{"1":{"get_star_ts":1639173303}}},"id":"1562613","last_star_ts":1639524515},"1855381":{"completion_day_level":{"2":{"1":{"get_star_ts":1638852339},"2":{"get_star_ts":1638856881}},"3":{"2":{"get_star_ts":1638891528},"1":{"get_star_ts":1638859285}},"4":{"1":{"get_star_ts":1638927788}},"1":{"1":{"get_star_ts":1638849023},"2":{"get_star_ts":1638850541}}},"local_score":27,"id":"1855381","last_star_ts":1638927788,"stars":7,"name":"cwithrow","global_score":0},"1696091":{"last_star_ts":1639360937,"id":"1696091","completion_day_level":{"3":{"1":{"get_star_ts":1638592204},"2":{"get_star_ts":1638670091}},"4":{"2":{"get_star_ts":1638762965},"1":{"get_star_ts":1638762263}},"5":{"2":{"get_star_ts":1638757930},"1":{"get_star_ts":1638751838}},"7":{"2":{"get_star_ts":1638938855},"1":{"get_star_ts":1638928669}},"6":{"2":{"get_star_ts":1638845000},"1":{"get_star_ts":1638841480}},"2":{"2":{"get_star_ts":1638588111},"1":{"get_star_ts":1638475583}},"9":{"1":{"get_star_ts":1639360937}},"1":{"2":{"get_star_ts":1638417360},"1":{"get_star_ts":1638416565}}},"local_score":77,"name":null,"global_score":0,"stars":15},"1635462":{"stars":9,"global_score":0,"name":"complexityOfDharma","completion_day_level":{"1":{"1":{"get_star_ts":1638379461},"2":{"get_star_ts":1638413714}},"3":{"1":{"get_star_ts":1638537772},"2":{"get_star_ts":1638592906}},"2":{"2":{"get_star_ts":1638428334},"1":{"get_star_ts":1638427290}},"6":{"1":{"get_star_ts":1638809977}},"7":{"1":{"get_star_ts":1638931038},"2":{"get_star_ts":1638933862}}},"id":"1635462","local_score":61,"last_star_ts":1638933862}},"event":"2021"}